{"version":"Sample 1.0.0","model":"moc/unitychan.moc","textures":["moc/unitychan.2048/texture_00.png"],"motions":{"":[{"file":"mtn/m_01.mtn"},{"file":"mtn/m_02.mtn"},{"file":"mtn/m_03.mtn"},{"file":"mtn/m_04.mtn"},{"file":"mtn/m_05.mtn"},{"file":"mtn/m_06.mtn"},{"file":"mtn/m_07.mtn"},{"file":"mtn/m_08.mtn"},{"file":"mtn/m_09.mtn"},{"file":"mtn/m_10.mtn"},{"file":"mtn/m_11.mtn"},{"file":"mtn/m_12.mtn"},{"file":"mtn/m_13.mtn"},{"file":"mtn/m_14.mtn"}],"idle":[{"file":"mtn/idle_01.mtn"},{"file":"mtn/idle_02.mtn"}]},"physics":"unitychan.physics.json"}