{"type":"Live2D Expression","fade_in":500,"fade_out":500,"params":[{"id":"PARAM_EYE_L_OPEN","val":0.86,"def":1},{"id":"PARAM_EYE_R_OPEN","val":0.86,"def":1},{"id":"PARAM_EYE_FORM","val":0.39},{"id":"PARAM_EYE_BALL_X","val":0.01},{"id":"PARAM_EYE_BALL_Y","val":-0.5},{"id":"PARAM_BROW_L_Y","val":0.35},{"id":"PARAM_BROW_R_Y","val":0.35},{"id":"PARAM_BROW_L_X","val":-0.5},{"id":"PARAM_BROW_R_X","val":-0.5},{"id":"PARAM_BROW_L_ANGLE","val":0.5},{"id":"PARAM_BROW_R_ANGLE","val":0.5},{"id":"PARAM_BROW_L_FORM","val":-1},{"id":"PARAM_BROW_R_FORM","val":-1},{"id":"PARAM_MOUTH_FORM","val":-1}]}